Metadata-Version: 1.0
Name: django-jqm
Version: 1.0.0a2
Summary: Pluggable JQuery Mobile templates for Django
Home-page: https://launchpad.net/django-jqm
Author: Mike C. Fletcher
Author-email: mcfletch@vrplumber.com
License: MIT
Platform: UNKNOWN
